README.md
setup.py
stonky/__init__.py
stonky/stonky.py
stonky/utils.py
stonky/strategies/loss_rebuy.py
stonky/strategies/mean_trend.py
stonky_bot.egg-info/PKG-INFO
stonky_bot.egg-info/SOURCES.txt
stonky_bot.egg-info/dependency_links.txt
stonky_bot.egg-info/entry_points.txt
stonky_bot.egg-info/requires.txt
stonky_bot.egg-info/top_level.txt